README.md
setup.py
VisionEngine/__init__.py
VisionEngine/main.py
VisionEngine.egg-info/PKG-INFO
VisionEngine.egg-info/SOURCES.txt
VisionEngine.egg-info/dependency_links.txt
VisionEngine.egg-info/top_level.txt
VisionEngine/base/__init__.py
VisionEngine/base/base_data_loader.py
VisionEngine/base/base_model.py
VisionEngine/base/base_trainer.py
VisionEngine/data_loaders/__init__.py
VisionEngine/data_loaders/data_loader.py
VisionEngine/data_loaders/datasets/__init__.py
VisionEngine/data_loaders/datasets/butterflies.py
VisionEngine/data_loaders/datasets/guppies.py
VisionEngine/extensions/__init__.py
VisionEngine/extensions/feature_attribution.py
VisionEngine/extensions/latent_evolution.py
VisionEngine/layers/__init__.py
VisionEngine/layers/noise_layer.py
VisionEngine/layers/perceptual_loss_layer.py
VisionEngine/layers/spectral_normalization_wrapper.py
VisionEngine/layers/squeeze_excite_layer.py
VisionEngine/layers/variational_layer.py
VisionEngine/models/__init__.py
VisionEngine/models/decoder.py
VisionEngine/models/encoder.py
VisionEngine/models/model.py
VisionEngine/trainers/__init__.py
VisionEngine/trainers/trainer.py
VisionEngine/utils/__init__.py
VisionEngine/utils/args.py
VisionEngine/utils/config.py
VisionEngine/utils/dirs.py
VisionEngine/utils/disentanglement_score.py
VisionEngine/utils/eval.py
VisionEngine/utils/factory.py
VisionEngine/utils/perceptual_loss.py
VisionEngine/utils/plotting.py