Metadata-Version: 1.0
Name: VisionEngine
Version: 0.1a0
Summary: VisionEngine is a machine learning framework for analyzing         natural color patterns
Home-page: http://github.com/ietheredge/VisionEngine
Author: R. Ian Etherdge
Author-email: ietheredge@ab.mpg.de
License: MIT
Platform: UNKNOWN
